send.py
Auto_Announcements-0.2.0.dist-info/LICENSE.md
Auto_Announcements-0.2.0.dist-info/METADATA
Auto_Announcements-0.2.0.dist-info/WHEEL
Auto_Announcements-0.2.0.dist-info/entry_points.txt
Auto_Announcements-0.2.0.dist-info/top_level.txt
Auto_Announcements-0.2.0.dist-info/RECORD
