Metadata-Version: 2.1
Name: Auto-Announcements
Version: 0.2.0
Summary: A bot framework that automatically sends announcements (or any other file) to a specified email address on Saturday night or when the script is run.
Home-page: https://github.com/Dog-Face-Development/Auto-Anouncements
Author: willtheorangeguy
License: # GNU GENERAL PUBLIC LICENSE        
Project-URL: Homepage, https://github.com/Dog-Face-Development/Auto-Anouncements
Project-URL: Bug Tracker, https://github.com/Dog-Face-Development/Auto-Anouncements
Keywords: auto announcement email bot cli
Classifier: Development Status :: 3 - Alpha
Classifier: License :: OSI Approved :: GNU General Public License v3 (GPLv3)
Classifier: Natural Language :: English
Classifier: Operating System :: OS Independent
Classifier: Topic :: Communications :: Email
Requires-Python: >=3.9
License-File: LICENSE.md
